{
  "1431799056211906582": {
    "active": true,
    "rareDrop": {
      "enabled": true,
      "intervalMinutes": 20,
      "maxActive": 2,
      "announceChannelId": "",
      "spawnChannelIds": [],
      "dropRatePercent": 100,
      "rewardCoinsMin": 25,
      "rewardCoinsMax": 250
    },
    "catDrop": {
      "enabled": true,
      "intervalMinutes": 20,
      "maxActive": 2,
      "announceChannelId": "",
      "spawnChannelIds": [],
      "rareCatChancePercent": 8,
      "rewardCoinsMin": 10,
      "rewardCoinsMax": 150
    },
    "pokemon": {
      "enabled": true,
      "privateOnly": true,
      "stage2Enabled": true,
      "battleEnabled": true,
      "tradingEnabled": true,
      "intervalMinutes": 20,
      "maxActive": 2,
      "spawnChannelIds": [],
      "catchCooldownSeconds": 5,
      "shinyChancePercent": 2,
      "legendaryChancePercent": 1,
      "baseRewardCoins": 50
    },
    "miniGames": {
      "rangeEnabled": true,
      "rangeChannelId": "",
      "rangeCooldownSeconds": 5,
      "truthDareEnabled": true,
      "truthDareChannelId": "",
      "truthDareCooldownSeconds": 5,
      "gunGameEnabled": true,
      "gunGameChannelId": "",
      "gunGameCooldownSeconds": 5,
      "dominionEnabled": true,
      "dominionChannelId": ""
    },
    "progression": {
      "enabled": true,
      "achievementsEnabled": true,
      "carolEnabled": true,
      "xpPerMessageMin": 5,
      "xpPerMessageMax": 15,
      "xpCooldownSeconds": 30,
      "dailyXpCap": 5000,
      "passiveVoiceXpPerMinute": 2,
      "levelUpChannelId": "",
      "announceLevelUp": true
    },
    "rewards": {
      "levelTiers": [
        {
          "level": 5,
          "roleId": "",
          "coins": 100,
          "itemTag": ""
        },
        {
          "level": 10,
          "roleId": "",
          "coins": 250,
          "itemTag": ""
        },
        {
          "level": 25,
          "roleId": "",
          "coins": 1000,
          "itemTag": ""
        }
      ]
    },
    "notes": "",
    "updatedAt": "2026-03-02T03:29:14.995Z"
  }
}